README.rst
setup.py
finist/__init__.py
finist/finist.py
finist.egg-info/PKG-INFO
finist.egg-info/SOURCES.txt
finist.egg-info/dependency_links.txt
finist.egg-info/pbr.json
finist.egg-info/requires.txt
finist.egg-info/top_level.txt