Metadata-Version: 1.0
Name: finist
Version: 0.1.2
Summary: Redis based Finite State Machine.
Home-page: https://github.com/sumanau7/finist
Author: Sumanau Sareen
Author-email: finist-python@googlegroups.com
License: APACHE
Keywords: redis state machine python
Platform: UNKNOWN
